pyjieba/__init__.py
pyjieba/dict/README.md
pyjieba/dict/__init__.py
pyjieba/dict/hmm_model.utf8
pyjieba/dict/idf.utf8
pyjieba/dict/jieba.dict.utf8
pyjieba/dict/stop_words.utf8
pyjieba/dict/user.dict.utf8
pyjieba/libs/__init__.py
pyjieba/libs/cppjieba_API_linux64.so
pyjieba/libs/cppjieba_API_osx64.so
pyjieba/libs/cppjieba_API_win64.dll
pyjieba-1.0.dist-info/METADATA
pyjieba-1.0.dist-info/RECORD
pyjieba-1.0.dist-info/WHEEL
pyjieba-1.0.dist-info/top_level.txt
