Metadata-Version: 2.1
Name: pyjieba
Version: 1.0
Summary: CPPJieba python wrapper
Home-page: https://github.com/chenrulongmaster/pyjieba
Author: chen ru long
Author-email: chenrulong0513.master@gmail.com
License: Apache-2.0
Keywords: jieba,cppjieba,pyjieba
Platform: any
